pyro_dash_py/__init__.py
pyro_dash_py/client.py
pyro_dash_py/core.py
pyro_dash_py/job.py
pyro_dash_py/job_file.py
pyro_dash_py/job_group.py
pyro_dash_py/project.py
pyro_dash_py/pyro_dash.py
pyro_dash_py-0.2.1.dist-info/METADATA
pyro_dash_py-0.2.1.dist-info/WHEEL
pyro_dash_py-0.2.1.dist-info/RECORD
