Metadata-Version: 2.3
Name: pyro-dash-py
Version: 0.2.1
Summary: A python sdk for the pyro-dashboard-api
Author: pyro-eng
Author-email: dev@pyrologix.com
Requires-Python: >=3.9,<4.0
Classifier: Programming Language :: Python :: 3
Classifier: Programming Language :: Python :: 3.9
Classifier: Programming Language :: Python :: 3.10
Classifier: Programming Language :: Python :: 3.11
Classifier: Programming Language :: Python :: 3.12
Classifier: Programming Language :: Python :: 3.13
Requires-Dist: requests (>=2.32.3,<3.0.0)
